{
  "stations": {
    "Yasu": {
      "name": "野洲",
      "lines": {
        "Tokaido": {
          "name": "東海道線",
          "up": {
            "weekday": [
              {
                "time": "07:12",
                "destination": "京都"
              },
              {
                "time": "07:25",
                "destination": "京都"
              }
            ],
            "holiday": []
          },
          "down": {
            "weekday": [
              {
                "time": "07:05",
                "destination": "米原"
              },
              {
                "time": "07:18",
                "destination": "米原"
              }
            ],
            "holiday": []
          }
        }
      }
    }
  }
}